dvis/__init__.py
dvis/dvis.py
dvis/dvis_cli.py
dvis/dvis_client.py
dvis/dvis_client_old.py
dvis/utils.py
dvis-0.9.1.0.dist-info/METADATA
dvis-0.9.1.0.dist-info/WHEEL
dvis-0.9.1.0.dist-info/entry_points.txt
dvis-0.9.1.0.dist-info/top_level.txt
dvis-0.9.1.0.dist-info/RECORD
