Metadata-Version: 2.1
Name: dvis
Version: 0.9.1.0
Summary: The best web-based visualizer
Home-page: https://github.com/SirWyver/dvis
Author: Norman Müller
Author-email: norman.mueller@tum.de
License: UNKNOWN
Platform: UNKNOWN
Classifier: Programming Language :: Python :: 3
Classifier: License :: OSI Approved :: MIT License
Classifier: Operating System :: OS Independent
Requires-Python: >=3.6
Requires-Dist: numpy
Requires-Dist: pillow (>=10.0)
Requires-Dist: trimesh
Requires-Dist: simple-websocket (>=0.2.0)
Requires-Dist: python-socketio (>=4.6.1)
Requires-Dist: eventlet
Requires-Dist: jinja2 (>=3.0.2)
Requires-Dist: werkzeug (>=2.0.3)
Requires-Dist: opencv-python
